{"v":"5.9.0","fr":25,"ip":0,"op":150,"w":1080,"h":1080,"nm":"Cure Cat_05","ddd":0,"assets":[{"id":"comp_0","nm":"05","fr":25,"layers":[{"ddd":0,"ind":1,"ty":4,"nm":"R Eyes","parent":11,"sr":1,"ks":{"o":{"a":0,"k":100,"ix":11},"r":{"a":0,"k":0,"ix":10},"p":{"a":0,"k":[108.108,132.176,0],"ix":2,"l":2},"a":{"a":0,"k":[13.366,4.797,0],"ix":1,"l":2},"s":{"a":1,"k":[{"i":{"x":[0.667,0.667,0.667],"y":[1,1,1]},"o":{"x":[0.333,0.333,0.333],"y":[0,0,0]},"t":0,"s":[100,100,100]},{"i":{"x":[0.667,0.667,0.667],"y":[1,1,1]},"o":{"x":[0.333,0.333,0.333],"y":[0,0,0]},"t":25,"s":[100,69,100]},{"t":50,"s":[100,100,100]}],"ix":6,"l":2,"x":"var $bm_rt;\n$bm_rt = loopOutDuration('cycle', 0);"}},"ao":0,"shapes":[{"ty":"gr","it":[{"ind":0,"ty":"sh","ix":1,"ks":{"a":0,"k":{"i":[[1.116,2.451],[-2.203,-1.099],[-2.281,-0.022],[-1.12,0.311],[-1.079,0.575],[-2.131,1.617],[2.218,-1.697],[2.953,0.058],[2.218,1.646]],"o":[[2.084,1.662],[2.192,1.104],[1.142,0.027],[1.123,-0.301],[2.185,-1.108],[-1.164,2.414],[-2.194,1.691],[-2.952,-0.028],[-2.214,-1.667]],"v":[[-13.116,-4.547],[-6.731,-0.321],[0.032,1.49],[3.434,1.042],[6.749,-0.273],[13.116,-4.547],[8.015,1.718],[0.001,4.489],[-7.97,1.677]],"c":true},"ix":2},"nm":"Path 1","mn":"ADBE Vector Shape - Group","hd":false},{"ty":"fl","c":{"a":0,"k":[0.003921568627,0,0.007843137255,1],"ix":4},"o":{"a":0,"k":100,"ix":5},"r":1,"bm":0,"nm":"Fill 1","mn":"ADBE Vector Graphic - Fill","hd":false},{"ty":"tr","p":{"a":0,"k":[13.366,4.796],"ix":2},"a":{"a":0,"k":[0,0],"ix":1},"s":{"a":0,"k":[100,100],"ix":3},"r":{"a":0,"k":0,"ix":6},"o":{"a":0,"k":100,"ix":7},"sk":{"a":0,"k":0,"ix":4},"sa":{"a":0,"k":0,"ix":5},"nm":"Transform"}],"nm":"Group 1","np":2,"cix":2,"bm":0,"ix":1,"mn":"ADBE Vector Group","hd":false}],"ip":0,"op":150,"st":0,"bm":0},{"ddd":0,"ind":2,"ty":4,"nm":"L Eyes","parent":11,"sr":1,"ks":{"o":{"a":0,"k":100,"ix":11},"r":{"a":0,"k":0,"ix":10},"p":{"a":0,"k":[214.083,147.964,0],"ix":2,"l":2},"a":{"a":0,"k":[12.544,7.312,0],"ix":1,"l":2},"s":{"a":1,"k":[{"i":{"x":[0.667,0.667,0.667],"y":[1,1,1]},"o":{"x":[0.333,0.333,0.333],"y":[0,0,0]},"t":0,"s":[100,100,100]},{"i":{"x":[0.667,0.667,0.667],"y":[1,1,1]},"o":{"x":[0.333,0.333,0.333],"y":[0,0,0]},"t":25,"s":[100,58,100]},{"t":50,"s":[100,100,100]}],"ix":6,"l":2,"x":"var $bm_rt;\n$bm_rt = loopOutDuration('cycle', 0);"}},"ao":0,"shapes":[{"ty":"gr","it":[{"ind":0,"ty":"sh","ix":1,"ks":{"a":0,"k":{"i":[[0.191,2.686],[-1.682,-1.797],[-2.131,-0.815],[-1.158,-0.098],[-1.212,0.163],[-2.562,0.772],[2.67,-0.817],[2.747,1.084],[1.505,2.315]],"o":[[1.375,2.283],[1.67,1.798],[1.06,0.424],[1.158,0.11],[2.434,-0.278],[-1.932,1.856],[-2.645,0.82],[-2.757,-1.055],[-1.496,-2.334]],"v":[[-12.294,-7.062],[-7.781,-0.876],[-2.073,3.177],[1.271,3.943],[4.837,3.865],[12.294,2.08],[5.33,6.172],[-3.147,5.977],[-9.638,0.565]],"c":true},"ix":2},"nm":"Path 1","mn":"ADBE Vector Shape - Group","hd":false},{"ty":"fl","c":{"a":0,"k":[0.003921568627,0,0.007843137255,1],"ix":4},"o":{"a":0,"k":100,"ix":5},"r":1,"bm":0,"nm":"Fill 1","mn":"ADBE Vector Graphic - Fill","hd":false},{"ty":"tr","p":{"a":0,"k":[12.544,7.312],"ix":2},"a":{"a":0,"k":[0,0],"ix":1},"s":{"a":0,"k":[100,100],"ix":3},"r":{"a":0,"k":0,"ix":6},"o":{"a":0,"k":100,"ix":7},"sk":{"a":0,"k":0,"ix":4},"sa":{"a":0,"k":0,"ix":5},"nm":"Transform"}],"nm":"Group 1","np":2,"cix":2,"bm":0,"ix":1,"mn":"ADBE Vector Group","hd":false}],"ip":0,"op":150,"st":0,"bm":0},{"ddd":0,"ind":3,"ty":4,"nm":"Staroke 7","sr":1,"ks":{"o":{"a":1,"k":[{"i":{"x":[0.667],"y":[1]},"o":{"x":[0.333],"y":[0]},"t":138,"s":[100]},{"t":150,"s":[0]}],"ix":11},"r":{"a":0,"k":0,"ix":10},"p":{"a":1,"k":[{"i":{"x":0.667,"y":1},"o":{"x":0.333,"y":0},"t":100,"s":[238.181,524.338,0],"to":[-87.875,18,0],"ti":[-40.375,37.5,0]},{"t":150,"s":[132.806,385.213,0]}],"ix":2,"l":2},"a":{"a":0,"k":[34.462,68.372,0],"ix":1,"l":2},"s":{"a":1,"k":[{"i":{"x":[0.667,0.667,0.667],"y":[1,1,1]},"o":{"x":[0.333,0.333,0.333],"y":[0,0,0]},"t":100,"s":[0,0,100]},{"i":{"x":[0.667,0.667,0.667],"y":[1,1,1]},"o":{"x":[0.333,0.333,0.333],"y":[0,0,0]},"t":125,"s":[150,150,100]},{"t":150,"s":[82.5,82.5,100]}],"ix":6,"l":2}},"ao":0,"shapes":[{"ty":"gr","it":[{"ind":0,"ty":"sh","ix":1,"ks":{"a":0,"k":{"i":[[4.167,0.399],[-4.167,0.203],[-2.083,0.062],[-2.083,0.031],[0,0],[0,0],[0,0],[0,0],[1.837,-1.246],[1.867,-1.201],[0,0],[-2.333,-0.095],[-2.333,-0.131],[-4.667,-0.439],[4.667,-0.21],[2.333,-0.092],[2.333,-0.06],[0,0],[0,0],[-1.825,1.262],[-1.851,1.225],[0,0],[0,0],[0,0],[2.083,0.072],[2.083,0.108]],"o":[[4.167,-0.399],[2.083,-0.108],[2.083,-0.072],[0,0],[0,0],[0,0],[0,0],[-1.816,1.275],[-1.842,1.238],[0,0],[2.333,0.06],[2.333,0.092],[4.667,0.209],[-4.667,0.439],[-2.333,0.13],[-2.333,0.095],[0,0],[0,0],[1.799,-1.299],[1.83,-1.254],[0,0],[0,0],[0,0],[-2.083,-0.031],[-2.083,-0.062],[-4.167,-0.203]],"v":[[-14.787,-7.559],[-2.287,-8.419],[3.963,-8.684],[10.213,-8.872],[14.419,-8.935],[10.952,-6.474],[5.524,-2.617],[0.05,1.172],[-5.463,4.901],[-11.01,8.583],[-11.787,6.06],[-4.787,6.232],[2.213,6.505],[16.213,7.441],[2.213,8.38],[-4.787,8.651],[-11.787,8.823],[-16.213,8.935],[-12.566,6.3],[-7.113,2.482],[-1.626,-1.289],[3.899,-5],[9.472,-8.643],[10.213,-6.245],[3.963,-6.434],[-2.287,-6.698]],"c":true},"ix":2},"nm":"Path 1","mn":"ADBE Vector Shape - Group","hd":false},{"ty":"fl","c":{"a":0,"k":[0.003921568627,0,0.007843137255,1],"ix":4},"o":{"a":0,"k":100,"ix":5},"r":1,"bm":0,"nm":"Fill 1","mn":"ADBE Vector Graphic - Fill","hd":false},{"ty":"tr","p":{"a":0,"k":[34.462,68.372],"ix":2},"a":{"a":0,"k":[0,0],"ix":1},"s":{"a":0,"k":[100,100],"ix":3},"r":{"a":0,"k":0,"ix":6},"o":{"a":0,"k":100,"ix":7},"sk":{"a":0,"k":0,"ix":4},"sa":{"a":0,"k":0,"ix":5},"nm":"Transform"}],"nm":"Group 3","np":2,"cix":2,"bm":0,"ix":1,"mn":"ADBE Vector Group","hd":false}],"ip":100,"op":250,"st":100,"bm":0},{"ddd":0,"ind":4,"ty":4,"nm":"Staroke 6","sr":1,"ks":{"o":{"a":1,"k":[{"i":{"x":[0.667],"y":[1]},"o":{"x":[0.333],"y":[0]},"t":111,"s":[100]},{"t":123,"s":[0]}],"ix":11},"r":{"a":0,"k":0,"ix":10},"p":{"a":1,"k":[{"i":{"x":0.667,"y":1},"o":{"x":0.333,"y":0},"t":73,"s":[238.181,524.338,0],"to":[-87.875,18,0],"ti":[-40.375,37.5,0]},{"t":123,"s":[132.806,385.213,0]}],"ix":2,"l":2},"a":{"a":0,"k":[34.462,68.372,0],"ix":1,"l":2},"s":{"a":1,"k":[{"i":{"x":[0.667,0.667,0.667],"y":[1,1,1]},"o":{"x":[0.333,0.333,0.333],"y":[0,0,0]},"t":73,"s":[0,0,100]},{"i":{"x":[0.667,0.667,0.667],"y":[1,1,1]},"o":{"x":[0.333,0.333,0.333],"y":[0,0,0]},"t":98,"s":[150,150,100]},{"t":123,"s":[82.5,82.5,100]}],"ix":6,"l":2}},"ao":0,"shapes":[{"ty":"gr","it":[{"ind":0,"ty":"sh","ix":1,"ks":{"a":0,"k":{"i":[[4.167,0.399],[-4.167,0.203],[-2.083,0.062],[-2.083,0.031],[0,0],[0,0],[0,0],[0,0],[1.837,-1.246],[1.867,-1.201],[0,0],[-2.333,-0.095],[-2.333,-0.131],[-4.667,-0.439],[4.667,-0.21],[2.333,-0.092],[2.333,-0.06],[0,0],[0,0],[-1.825,1.262],[-1.851,1.225],[0,0],[0,0],[0,0],[2.083,0.072],[2.083,0.108]],"o":[[4.167,-0.399],[2.083,-0.108],[2.083,-0.072],[0,0],[0,0],[0,0],[0,0],[-1.816,1.275],[-1.842,1.238],[0,0],[2.333,0.06],[2.333,0.092],[4.667,0.209],[-4.667,0.439],[-2.333,0.13],[-2.333,0.095],[0,0],[0,0],[1.799,-1.299],[1.83,-1.254],[0,0],[0,0],[0,0],[-2.083,-0.031],[-2.083,-0.062],[-4.167,-0.203]],"v":[[-14.787,-7.559],[-2.287,-8.419],[3.963,-8.684],[10.213,-8.872],[14.419,-8.935],[10.952,-6.474],[5.524,-2.617],[0.05,1.172],[-5.463,4.901],[-11.01,8.583],[-11.787,6.06],[-4.787,6.232],[2.213,6.505],[16.213,7.441],[2.213,8.38],[-4.787,8.651],[-11.787,8.823],[-16.213,8.935],[-12.566,6.3],[-7.113,2.482],[-1.626,-1.289],[3.899,-5],[9.472,-8.643],[10.213,-6.245],[3.963,-6.434],[-2.287,-6.698]],"c":true},"ix":2},"nm":"Path 1","mn":"ADBE Vector Shape - Group","hd":false},{"ty":"fl","c":{"a":0,"k":[0.003921568627,0,0.007843137255,1],"ix":4},"o":{"a":0,"k":100,"ix":5},"r":1,"bm":0,"nm":"Fill 1","mn":"ADBE Vector Graphic - Fill","hd":false},{"ty":"tr","p":{"a":0,"k":[34.462,68.372],"ix":2},"a":{"a":0,"k":[0,0],"ix":1},"s":{"a":0,"k":[100,100],"ix":3},"r":{"a":0,"k":0,"ix":6},"o":{"a":0,"k":100,"ix":7},"sk":{"a":0,"k":0,"ix":4},"sa":{"a":0,"k":0,"ix":5},"nm":"Transform"}],"nm":"Group 3","np":2,"cix":2,"bm":0,"ix":1,"mn":"ADBE Vector Group","hd":false}],"ip":73,"op":223,"st":73,"bm":0},{"ddd":0,"ind":5,"ty":4,"nm":"Staroke 5","sr":1,"ks":{"o":{"a":1,"k":[{"i":{"x":[0.667],"y":[1]},"o":{"x":[0.333],"y":[0]},"t":89,"s":[100]},{"t":101,"s":[0]}],"ix":11},"r":{"a":0,"k":0,"ix":10},"p":{"a":1,"k":[{"i":{"x":0.667,"y":1},"o":{"x":0.333,"y":0},"t":51,"s":[238.181,524.338,0],"to":[-87.875,18,0],"ti":[-40.375,37.5,0]},{"t":101,"s":[132.806,385.213,0]}],"ix":2,"l":2},"a":{"a":0,"k":[34.462,68.372,0],"ix":1,"l":2},"s":{"a":1,"k":[{"i":{"x":[0.667,0.667,0.667],"y":[1,1,1]},"o":{"x":[0.333,0.333,0.333],"y":[0,0,0]},"t":51,"s":[0,0,100]},{"i":{"x":[0.667,0.667,0.667],"y":[1,1,1]},"o":{"x":[0.333,0.333,0.333],"y":[0,0,0]},"t":76,"s":[150,150,100]},{"t":101,"s":[82.5,82.5,100]}],"ix":6,"l":2}},"ao":0,"shapes":[{"ty":"gr","it":[{"ind":0,"ty":"sh","ix":1,"ks":{"a":0,"k":{"i":[[4.167,0.399],[-4.167,0.203],[-2.083,0.062],[-2.083,0.031],[0,0],[0,0],[0,0],[0,0],[1.837,-1.246],[1.867,-1.201],[0,0],[-2.333,-0.095],[-2.333,-0.131],[-4.667,-0.439],[4.667,-0.21],[2.333,-0.092],[2.333,-0.06],[0,0],[0,0],[-1.825,1.262],[-1.851,1.225],[0,0],[0,0],[0,0],[2.083,0.072],[2.083,0.108]],"o":[[4.167,-0.399],[2.083,-0.108],[2.083,-0.072],[0,0],[0,0],[0,0],[0,0],[-1.816,1.275],[-1.842,1.238],[0,0],[2.333,0.06],[2.333,0.092],[4.667,0.209],[-4.667,0.439],[-2.333,0.13],[-2.333,0.095],[0,0],[0,0],[1.799,-1.299],[1.83,-1.254],[0,0],[0,0],[0,0],[-2.083,-0.031],[-2.083,-0.062],[-4.167,-0.203]],"v":[[-14.787,-7.559],[-2.287,-8.419],[3.963,-8.684],[10.213,-8.872],[14.419,-8.935],[10.952,-6.474],[5.524,-2.617],[0.05,1.172],[-5.463,4.901],[-11.01,8.583],[-11.787,6.06],[-4.787,6.232],[2.213,6.505],[16.213,7.441],[2.213,8.38],[-4.787,8.651],[-11.787,8.823],[-16.213,8.935],[-12.566,6.3],[-7.113,2.482],[-1.626,-1.289],[3.899,-5],[9.472,-8.643],[10.213,-6.245],[3.963,-6.434],[-2.287,-6.698]],"c":true},"ix":2},"nm":"Path 1","mn":"ADBE Vector Shape - Group","hd":false},{"ty":"fl","c":{"a":0,"k":[0.003921568627,0,0.007843137255,1],"ix":4},"o":{"a":0,"k":100,"ix":5},"r":1,"bm":0,"nm":"Fill 1","mn":"ADBE Vector Graphic - Fill","hd":false},{"ty":"tr","p":{"a":0,"k":[34.462,68.372],"ix":2},"a":{"a":0,"k":[0,0],"ix":1},"s":{"a":0,"k":[100,100],"ix":3},"r":{"a":0,"k":0,"ix":6},"o":{"a":0,"k":100,"ix":7},"sk":{"a":0,"k":0,"ix":4},"sa":{"a":0,"k":0,"ix":5},"nm":"Transform"}],"nm":"Group 3","np":2,"cix":2,"bm":0,"ix":1,"mn":"ADBE Vector Group","hd":false}],"ip":51,"op":201,"st":51,"bm":0},{"ddd":0,"ind":6,"ty":4,"nm":"Staroke 4","sr":1,"ks":{"o":{"a":1,"k":[{"i":{"x":[0.667],"y":[1]},"o":{"x":[0.333],"y":[0]},"t":64,"s":[100]},{"t":76,"s":[0]}],"ix":11},"r":{"a":0,"k":0,"ix":10},"p":{"a":1,"k":[{"i":{"x":0.667,"y":1},"o":{"x":0.333,"y":0},"t":26,"s":[238.181,524.338,0],"to":[-87.875,18,0],"ti":[-40.375,37.5,0]},{"t":76,"s":[132.806,385.213,0]}],"ix":2,"l":2},"a":{"a":0,"k":[34.462,68.372,0],"ix":1,"l":2},"s":{"a":1,"k":[{"i":{"x":[0.667,0.667,0.667],"y":[1,1,1]},"o":{"x":[0.333,0.333,0.333],"y":[0,0,0]},"t":26,"s":[0,0,100]},{"i":{"x":[0.667,0.667,0.667],"y":[1,1,1]},"o":{"x":[0.333,0.333,0.333],"y":[0,0,0]},"t":51,"s":[150,150,100]},{"t":76,"s":[82.5,82.5,100]}],"ix":6,"l":2}},"ao":0,"shapes":[{"ty":"gr","it":[{"ind":0,"ty":"sh","ix":1,"ks":{"a":0,"k":{"i":[[4.167,0.399],[-4.167,0.203],[-2.083,0.062],[-2.083,0.031],[0,0],[0,0],[0,0],[0,0],[1.837,-1.246],[1.867,-1.201],[0,0],[-2.333,-0.095],[-2.333,-0.131],[-4.667,-0.439],[4.667,-0.21],[2.333,-0.092],[2.333,-0.06],[0,0],[0,0],[-1.825,1.262],[-1.851,1.225],[0,0],[0,0],[0,0],[2.083,0.072],[2.083,0.108]],"o":[[4.167,-0.399],[2.083,-0.108],[2.083,-0.072],[0,0],[0,0],[0,0],[0,0],[-1.816,1.275],[-1.842,1.238],[0,0],[2.333,0.06],[2.333,0.092],[4.667,0.209],[-4.667,0.439],[-2.333,0.13],[-2.333,0.095],[0,0],[0,0],[1.799,-1.299],[1.83,-1.254],[0,0],[0,0],[0,0],[-2.083,-0.031],[-2.083,-0.062],[-4.167,-0.203]],"v":[[-14.787,-7.559],[-2.287,-8.419],[3.963,-8.684],[10.213,-8.872],[14.419,-8.935],[10.952,-6.474],[5.524,-2.617],[0.05,1.172],[-5.463,4.901],[-11.01,8.583],[-11.787,6.06],[-4.787,6.232],[2.213,6.505],[16.213,7.441],[2.213,8.38],[-4.787,8.651],[-11.787,8.823],[-16.213,8.935],[-12.566,6.3],[-7.113,2.482],[-1.626,-1.289],[3.899,-5],[9.472,-8.643],[10.213,-6.245],[3.963,-6.434],[-2.287,-6.698]],"c":true},"ix":2},"nm":"Path 1","mn":"ADBE Vector Shape - Group","hd":false},{"ty":"fl","c":{"a":0,"k":[0.003921568627,0,0.007843137255,1],"ix":4},"o":{"a":0,"k":100,"ix":5},"r":1,"bm":0,"nm":"Fill 1","mn":"ADBE Vector Graphic - Fill","hd":false},{"ty":"tr","p":{"a":0,"k":[34.462,68.372],"ix":2},"a":{"a":0,"k":[0,0],"ix":1},"s":{"a":0,"k":[100,100],"ix":3},"r":{"a":0,"k":0,"ix":6},"o":{"a":0,"k":100,"ix":7},"sk":{"a":0,"k":0,"ix":4},"sa":{"a":0,"k":0,"ix":5},"nm":"Transform"}],"nm":"Group 3","np":2,"cix":2,"bm":0,"ix":1,"mn":"ADBE Vector Group","hd":false}],"ip":26,"op":176,"st":26,"bm":0},{"ddd":0,"ind":7,"ty":4,"nm":"Staroke 3","sr":1,"ks":{"o":{"a":1,"k":[{"i":{"x":[0.667],"y":[1]},"o":{"x":[0.333],"y":[0]},"t":49,"s":[100]},{"t":61,"s":[0]}],"ix":11},"r":{"a":0,"k":0,"ix":10},"p":{"a":1,"k":[{"i":{"x":0.667,"y":1},"o":{"x":0.333,"y":0},"t":11,"s":[238.181,524.338,0],"to":[-87.875,18,0],"ti":[-40.375,37.5,0]},{"t":61,"s":[132.806,385.213,0]}],"ix":2,"l":2},"a":{"a":0,"k":[34.462,68.372,0],"ix":1,"l":2},"s":{"a":1,"k":[{"i":{"x":[0.667,0.667,0.667],"y":[1,1,1]},"o":{"x":[0.333,0.333,0.333],"y":[0,0,0]},"t":11,"s":[0,0,100]},{"i":{"x":[0.667,0.667,0.667],"y":[1,1,1]},"o":{"x":[0.333,0.333,0.333],"y":[0,0,0]},"t":36,"s":[150,150,100]},{"t":61,"s":[82.5,82.5,100]}],"ix":6,"l":2}},"ao":0,"shapes":[{"ty":"gr","it":[{"ind":0,"ty":"sh","ix":1,"ks":{"a":0,"k":{"i":[[4.167,0.399],[-4.167,0.203],[-2.083,0.062],[-2.083,0.031],[0,0],[0,0],[0,0],[0,0],[1.837,-1.246],[1.867,-1.201],[0,0],[-2.333,-0.095],[-2.333,-0.131],[-4.667,-0.439],[4.667,-0.21],[2.333,-0.092],[2.333,-0.06],[0,0],[0,0],[-1.825,1.262],[-1.851,1.225],[0,0],[0,0],[0,0],[2.083,0.072],[2.083,0.108]],"o":[[4.167,-0.399],[2.083,-0.108],[2.083,-0.072],[0,0],[0,0],[0,0],[0,0],[-1.816,1.275],[-1.842,1.238],[0,0],[2.333,0.06],[2.333,0.092],[4.667,0.209],[-4.667,0.439],[-2.333,0.13],[-2.333,0.095],[0,0],[0,0],[1.799,-1.299],[1.83,-1.254],[0,0],[0,0],[0,0],[-2.083,-0.031],[-2.083,-0.062],[-4.167,-0.203]],"v":[[-14.787,-7.559],[-2.287,-8.419],[3.963,-8.684],[10.213,-8.872],[14.419,-8.935],[10.952,-6.474],[5.524,-2.617],[0.05,1.172],[-5.463,4.901],[-11.01,8.583],[-11.787,6.06],[-4.787,6.232],[2.213,6.505],[16.213,7.441],[2.213,8.38],[-4.787,8.651],[-11.787,8.823],[-16.213,8.935],[-12.566,6.3],[-7.113,2.482],[-1.626,-1.289],[3.899,-5],[9.472,-8.643],[10.213,-6.245],[3.963,-6.434],[-2.287,-6.698]],"c":true},"ix":2},"nm":"Path 1","mn":"ADBE Vector Shape - Group","hd":false},{"ty":"fl","c":{"a":0,"k":[0.003921568627,0,0.007843137255,1],"ix":4},"o":{"a":0,"k":100,"ix":5},"r":1,"bm":0,"nm":"Fill 1","mn":"ADBE Vector Graphic - Fill","hd":false},{"ty":"tr","p":{"a":0,"k":[34.462,68.372],"ix":2},"a":{"a":0,"k":[0,0],"ix":1},"s":{"a":0,"k":[100,100],"ix":3},"r":{"a":0,"k":0,"ix":6},"o":{"a":0,"k":100,"ix":7},"sk":{"a":0,"k":0,"ix":4},"sa":{"a":0,"k":0,"ix":5},"nm":"Transform"}],"nm":"Group 3","np":2,"cix":2,"bm":0,"ix":1,"mn":"ADBE Vector Group","hd":false}],"ip":11,"op":161,"st":11,"bm":0},{"ddd":0,"ind":8,"ty":4,"nm":"Staroke 2","sr":1,"ks":{"o":{"a":1,"k":[{"i":{"x":[0.667],"y":[1]},"o":{"x":[0.333],"y":[0]},"t":38,"s":[100]},{"t":50,"s":[0]}],"ix":11},"r":{"a":0,"k":0,"ix":10},"p":{"a":1,"k":[{"i":{"x":0.667,"y":1},"o":{"x":0.333,"y":0},"t":0,"s":[238.181,524.338,0],"to":[-87.875,18,0],"ti":[-40.375,37.5,0]},{"t":50,"s":[132.806,385.213,0]}],"ix":2,"l":2},"a":{"a":0,"k":[34.462,68.372,0],"ix":1,"l":2},"s":{"a":1,"k":[{"i":{"x":[0.667,0.667,0.667],"y":[1,1,1]},"o":{"x":[0.333,0.333,0.333],"y":[0,0,0]},"t":0,"s":[0,0,100]},{"i":{"x":[0.667,0.667,0.667],"y":[1,1,1]},"o":{"x":[0.333,0.333,0.333],"y":[0,0,0]},"t":25,"s":[150,150,100]},{"t":50,"s":[82.5,82.5,100]}],"ix":6,"l":2}},"ao":0,"shapes":[{"ty":"gr","it":[{"ind":0,"ty":"sh","ix":1,"ks":{"a":0,"k":{"i":[[4.167,0.399],[-4.167,0.203],[-2.083,0.062],[-2.083,0.031],[0,0],[0,0],[0,0],[0,0],[1.837,-1.246],[1.867,-1.201],[0,0],[-2.333,-0.095],[-2.333,-0.131],[-4.667,-0.439],[4.667,-0.21],[2.333,-0.092],[2.333,-0.06],[0,0],[0,0],[-1.825,1.262],[-1.851,1.225],[0,0],[0,0],[0,0],[2.083,0.072],[2.083,0.108]],"o":[[4.167,-0.399],[2.083,-0.108],[2.083,-0.072],[0,0],[0,0],[0,0],[0,0],[-1.816,1.275],[-1.842,1.238],[0,0],[2.333,0.06],[2.333,0.092],[4.667,0.209],[-4.667,0.439],[-2.333,0.13],[-2.333,0.095],[0,0],[0,0],[1.799,-1.299],[1.83,-1.254],[0,0],[0,0],[0,0],[-2.083,-0.031],[-2.083,-0.062],[-4.167,-0.203]],"v":[[-14.787,-7.559],[-2.287,-8.419],[3.963,-8.684],[10.213,-8.872],[14.419,-8.935],[10.952,-6.474],[5.524,-2.617],[0.05,1.172],[-5.463,4.901],[-11.01,8.583],[-11.787,6.06],[-4.787,6.232],[2.213,6.505],[16.213,7.441],[2.213,8.38],[-4.787,8.651],[-11.787,8.823],[-16.213,8.935],[-12.566,6.3],[-7.113,2.482],[-1.626,-1.289],[3.899,-5],[9.472,-8.643],[10.213,-6.245],[3.963,-6.434],[-2.287,-6.698]],"c":true},"ix":2},"nm":"Path 1","mn":"ADBE Vector Shape - Group","hd":false},{"ty":"fl","c":{"a":0,"k":[0.003921568627,0,0.007843137255,1],"ix":4},"o":{"a":0,"k":100,"ix":5},"r":1,"bm":0,"nm":"Fill 1","mn":"ADBE Vector Graphic - Fill","hd":false},{"ty":"tr","p":{"a":0,"k":[34.462,68.372],"ix":2},"a":{"a":0,"k":[0,0],"ix":1},"s":{"a":0,"k":[100,100],"ix":3},"r":{"a":0,"k":0,"ix":6},"o":{"a":0,"k":100,"ix":7},"sk":{"a":0,"k":0,"ix":4},"sa":{"a":0,"k":0,"ix":5},"nm":"Transform"}],"nm":"Group 3","np":2,"cix":2,"bm":0,"ix":1,"mn":"ADBE Vector Group","hd":false}],"ip":0,"op":150,"st":0,"bm":0},{"ddd":0,"ind":10,"ty":4,"nm":"Tail","parent":12,"sr":1,"ks":{"o":{"a":0,"k":100,"ix":11},"r":{"a":1,"k":[{"i":{"x":[0.667],"y":[1]},"o":{"x":[0.333],"y":[0]},"t":25,"s":[0]},{"i":{"x":[0.667],"y":[1]},"o":{"x":[0.333],"y":[0]},"t":37.5,"s":[51]},{"t":50,"s":[0]}],"ix":10,"x":"var $bm_rt;\n$bm_rt = loopOutDuration('cycle', 0);"},"p":{"a":0,"k":[427.431,242.678,0],"ix":2,"l":2},"a":{"a":0,"k":[214.507,10.694,0],"ix":1,"l":2},"s":{"a":0,"k":[100,100,100],"ix":6,"l":2}},"ao":0,"shapes":[{"ty":"gr","it":[{"ind":0,"ty":"sh","ix":1,"ks":{"a":0,"k":{"i":[[0.315,-8.25],[-9.979,1.832],[3.098,10.442],[10.695,-0.97]],"o":[[10.992,-1.027],[0.764,-7.901],[-10.167,1.958],[2.001,7.186]],"v":[[-14.273,16.893],[17.36,12.664],[13.253,-16.893],[-18.124,-12.482]],"c":true},"ix":2},"nm":"Path 1","mn":"ADBE Vector Shape - Group","hd":false},{"ty":"fl","c":{"a":0,"k":[0.784313785329,0.572549019608,0.321568627451,1],"ix":4},"o":{"a":0,"k":100,"ix":5},"r":1,"bm":0,"nm":"Fill 1","mn":"ADBE Vector Graphic - Fill","hd":false},{"ty":"tr","p":{"a":0,"k":[192.579,98.42],"ix":2},"a":{"a":0,"k":[0,0],"ix":1},"s":{"a":0,"k":[100,100],"ix":3},"r":{"a":0,"k":0,"ix":6},"o":{"a":0,"k":100,"ix":7},"sk":{"a":0,"k":0,"ix":4},"sa":{"a":0,"k":0,"ix":5},"nm":"Transform"}],"nm":"Group 1","np":2,"cix":2,"bm":0,"ix":1,"mn":"ADBE Vector Group","hd":false},{"ty":"gr","it":[{"ind":0,"ty":"sh","ix":1,"ks":{"a":0,"k":{"i":[[5.947,-6.43],[-11.198,-3.214],[-3.512,9.5],[8.675,4.263]],"o":[[9.571,5.06],[5.738,-7.422],[-10.748,-2.674],[-2.865,6.29]],"v":[[-22.982,6.3],[8.256,18.743],[22.982,-8.383],[-6.354,-18.743]],"c":true},"ix":2},"nm":"Path 1","mn":"ADBE Vector Shape - Group","hd":false},{"ty":"fl","c":{"a":0,"k":[0.784313785329,0.572549019608,0.321568627451,1],"ix":4},"o":{"a":0,"k":100,"ix":5},"r":1,"bm":0,"nm":"Fill 1","mn":"ADBE Vector Graphic - Fill","hd":false},{"ty":"tr","p":{"a":0,"k":[57.328,88.578],"ix":2},"a":{"a":0,"k":[0,0],"ix":1},"s":{"a":0,"k":[100,100],"ix":3},"r":{"a":0,"k":0,"ix":6},"o":{"a":0,"k":100,"ix":7},"sk":{"a":0,"k":0,"ix":4},"sa":{"a":0,"k":0,"ix":5},"nm":"Transform"}],"nm":"Group 2","np":2,"cix":2,"bm":0,"ix":2,"mn":"ADBE Vector Group","hd":false},{"ty":"gr","it":[{"ind":0,"ty":"sh","ix":1,"ks":{"a":0,"k":{"i":[[-2.581,-3.373],[-11.468,-2.805],[11.039,6.733],[3.109,-10.21]],"o":[[4.65,-8.478],[-4.497,-9.196],[-9.71,4.685],[5.986,3.291]],"v":[[-8.105,17.081],[21.005,6.988],[-2.692,-17.081],[-21.005,6.956]],"c":true},"ix":2},"nm":"Path 1","mn":"ADBE Vector Shape - Group","hd":false},{"ty":"fl","c":{"a":0,"k":[0.784313785329,0.572549019608,0.321568627451,1],"ix":4},"o":{"a":0,"k":100,"ix":5},"r":1,"bm":0,"nm":"Fill 1","mn":"ADBE Vector Graphic - Fill","hd":false},{"ty":"tr","p":{"a":0,"k":[257.418,32.016],"ix":2},"a":{"a":0,"k":[0,0],"ix":1},"s":{"a":0,"k":[100,100],"ix":3},"r":{"a":0,"k":0,"ix":6},"o":{"a":0,"k":100,"ix":7},"sk":{"a":0,"k":0,"ix":4},"sa":{"a":0,"k":0,"ix":5},"nm":"Transform"}],"nm":"Group 3","np":2,"cix":2,"bm":0,"ix":3,"mn":"ADBE Vector Group","hd":false},{"ty":"gr","it":[{"ind":0,"ty":"sh","ix":1,"ks":{"a":0,"k":{"i":[[0.025,10.619],[10.211,0.97],[2.94,-6.866],[-11.002,-0.037]],"o":[[-10.603,0.071],[-0.515,8.305],[10.898,1.114],[2.82,-7.933]],"v":[[18.598,-14.249],[-12.74,-15.545],[-18.623,13.762],[14.31,15.545]],"c":true},"ix":2},"nm":"Path 1","mn":"ADBE Vector Shape - Group","hd":false},{"ty":"fl","c":{"a":0,"k":[0.784313785329,0.572549019608,0.321568627451,1],"ix":4},"o":{"a":0,"k":100,"ix":5},"r":1,"bm":0,"nm":"Fill 1","mn":"ADBE Vector Graphic - Fill","hd":false},{"ty":"tr","p":{"a":0,"k":[127.667,101.557],"ix":2},"a":{"a":0,"k":[0,0],"ix":1},"s":{"a":0,"k":[100,100],"ix":3},"r":{"a":0,"k":0,"ix":6},"o":{"a":0,"k":100,"ix":7},"sk":{"a":0,"k":0,"ix":4},"sa":{"a":0,"k":0,"ix":5},"nm":"Transform"}],"nm":"Group 4","np":2,"cix":2,"bm":0,"ix":4,"mn":"ADBE Vector Group","hd":false},{"ty":"gr","it":[{"ind":0,"ty":"sh","ix":1,"ks":{"a":0,"k":{"i":[[-5.828,6.714],[10.638,4.193],[12.524,-3.75],[-2.433,-11.566]],"o":[[-1.569,-7.97],[-3.295,5.009],[9.302,1.301],[10.084,-4.463]],"v":[[22.407,2.187],[1.161,-19.092],[-22.407,-5.066],[-1.602,19.092]],"c":true},"ix":2},"nm":"Path 1","mn":"ADBE Vector Shape - Group","hd":false},{"ty":"fl","c":{"a":0,"k":[0.784313785329,0.572549019608,0.321568627451,1],"ix":4},"o":{"a":0,"k":100,"ix":5},"r":1,"bm":0,"nm":"Fill 1","mn":"ADBE Vector Graphic - Fill","hd":false},{"ty":"tr","p":{"a":0,"k":[249.552,81.506],"ix":2},"a":{"a":0,"k":[0,0],"ix":1},"s":{"a":0,"k":[100,100],"ix":3},"r":{"a":0,"k":0,"ix":6},"o":{"a":0,"k":100,"ix":7},"sk":{"a":0,"k":0,"ix":4},"sa":{"a":0,"k":0,"ix":5},"nm":"Transform"}],"nm":"Group 5","np":2,"cix":2,"bm":0,"ix":5,"mn":"ADBE Vector Group","hd":false},{"ty":"gr","it":[{"ind":0,"ty":"sh","ix":1,"ks":{"a":0,"k":{"i":[[32.563,0],[29.512,31.932],[-6.06,5.601],[-5.589,-6.068],[-67.752,18.166],[-0.044,6.473],[24.371,6.788],[-2.222,7.944],[-7.991,-2.211],[0.113,-24.101],[31.24,-8.372]],"o":[[-53.052,0],[-5.586,-6.06],[6.058,-5.565],[33.955,36.771],[19.232,-5.149],[0.023,-7.551],[-7.944,-2.211],[2.222,-7.943],[35.952,10.011],[-0.11,22.431],[-24.91,6.664]],"v":[[1.738,58.444],[-135.671,14.953],[-134.839,-6.155],[-113.722,-5.314],[83.382,18.552],[111.275,-1.913],[75.885,-27.461],[65.517,-45.853],[83.92,-56.233],[141.144,-1.768],[91.1,47.414]],"c":true},"ix":2},"nm":"Path 1","mn":"ADBE Vector Shape - Group","hd":false},{"ty":"fl","c":{"a":0,"k":[0.666666666667,0.411764735802,0.286274509804,1],"ix":4},"o":{"a":0,"k":100,"ix":5},"r":1,"bm":0,"nm":"Fill 1","mn":"ADBE Vector Graphic - Fill","hd":false},{"ty":"tr","p":{"a":0,"k":[141.507,58.695],"ix":2},"a":{"a":0,"k":[0,0],"ix":1},"s":{"a":0,"k":[100,100],"ix":3},"r":{"a":0,"k":0,"ix":6},"o":{"a":0,"k":100,"ix":7},"sk":{"a":0,"k":0,"ix":4},"sa":{"a":0,"k":0,"ix":5},"nm":"Transform"}],"nm":"Group 6","np":2,"cix":2,"bm":0,"ix":6,"mn":"ADBE Vector Group","hd":false}],"ip":0,"op":150,"st":0,"bm":0},{"ddd":0,"ind":11,"ty":4,"nm":"Face","sr":1,"ks":{"o":{"a":0,"k":100,"ix":11},"r":{"a":1,"k":[{"i":{"x":[0.667],"y":[1]},"o":{"x":[0.333],"y":[0]},"t":0,"s":[0]},{"i":{"x":[0.667],"y":[1]},"o":{"x":[0.333],"y":[0]},"t":74.5,"s":[-15.307]},{"t":149,"s":[0]}],"ix":10},"p":{"a":1,"k":[{"i":{"x":0.667,"y":1},"o":{"x":0.333,"y":0},"t":0,"s":[412.234,502.819,0],"to":[0,3.75,0],"ti":[0,0,0]},{"i":{"x":0.667,"y":1},"o":{"x":0.333,"y":0},"t":74.5,"s":[412.234,525.319,0],"to":[0,0,0],"ti":[0,3.75,0]},{"t":149,"s":[412.234,502.819,0]}],"ix":2,"l":2},"a":{"a":0,"k":[162.43,149.898,0],"ix":1,"l":2},"s":{"a":0,"k":[150,150,100],"ix":6,"l":2}},"ao":0,"shapes":[{"ty":"gr","it":[{"ind":0,"ty":"sh","ix":1,"ks":{"a":0,"k":{"i":[[0,0],[-10.253,1.983]],"o":[[0,0],[0,0]],"v":[[-9.377,-3.109],[9.377,1.125]],"c":false},"ix":2},"nm":"Path 1","mn":"ADBE Vector Shape - Group","hd":false},{"ty":"st","c":{"a":0,"k":[0.003921568627,0,0.007843137255,1],"ix":3},"o":{"a":0,"k":100,"ix":4},"w":{"a":0,"k":2,"ix":5},"lc":1,"lj":1,"ml":10,"bm":0,"nm":"Stroke 1","mn":"ADBE Vector Graphic - Stroke","hd":false},{"ty":"tr","p":{"a":0,"k":[152.635,183.262],"ix":2},"a":{"a":0,"k":[0,0],"ix":1},"s":{"a":0,"k":[100,100],"ix":3},"r":{"a":0,"k":0,"ix":6},"o":{"a":0,"k":100,"ix":7},"sk":{"a":0,"k":0,"ix":4},"sa":{"a":0,"k":0,"ix":5},"nm":"Transform"}],"nm":"Group 1","np":2,"cix":2,"bm":0,"ix":1,"mn":"ADBE Vector Group","hd":false},{"ty":"gr","it":[{"ind":0,"ty":"sh","ix":1,"ks":{"a":0,"k":{"i":[[-0.417,-1.844],[7.641,-1.729],[0.418,1.844],[-7.64,1.729]],"o":[[0.418,1.844],[-7.64,1.73],[-0.417,-1.845],[7.64,-1.729]],"v":[[13.834,-3.132],[0.756,3.339],[-13.834,3.131],[-0.757,-3.339]],"c":true},"ix":2},"nm":"Path 1","mn":"ADBE Vector Shape - Group","hd":false},{"ty":"fl","c":{"a":0,"k":[0.003921568627,0,0.007843137255,1],"ix":4},"o":{"a":0,"k":100,"ix":5},"r":1,"bm":0,"nm":"Fill 1","mn":"ADBE Vector Graphic - Fill","hd":false},{"ty":"tr","p":{"a":0,"k":[108.199,91.929],"ix":2},"a":{"a":0,"k":[0,0],"ix":1},"s":{"a":0,"k":[100,100],"ix":3},"r":{"a":0,"k":0,"ix":6},"o":{"a":0,"k":100,"ix":7},"sk":{"a":0,"k":0,"ix":4},"sa":{"a":0,"k":0,"ix":5},"nm":"Transform"}],"nm":"Group 2","np":2,"cix":2,"bm":0,"ix":2,"mn":"ADBE Vector Group","hd":false},{"ty":"gr","it":[{"ind":0,"ty":"sh","ix":1,"ks":{"a":0,"k":{"i":[[0.761,-1.731],[7.171,3.152],[-0.761,1.731],[-7.171,-3.152]],"o":[[-0.761,1.731],[-7.171,-3.152],[0.76,-1.731],[7.171,3.152]],"v":[[12.984,5.707],[-1.378,3.134],[-12.984,-5.707],[1.377,-3.134]],"c":true},"ix":2},"nm":"Path 1","mn":"ADBE Vector Shape - Group","hd":false},{"ty":"fl","c":{"a":0,"k":[0.003921568627,0,0.007843137255,1],"ix":4},"o":{"a":0,"k":100,"ix":5},"r":1,"bm":0,"nm":"Fill 1","mn":"ADBE Vector Graphic - Fill","hd":false},{"ty":"tr","p":{"a":0,"k":[224.596,118.338],"ix":2},"a":{"a":0,"k":[0,0],"ix":1},"s":{"a":0,"k":[100,100],"ix":3},"r":{"a":0,"k":0,"ix":6},"o":{"a":0,"k":100,"ix":7},"sk":{"a":0,"k":0,"ix":4},"sa":{"a":0,"k":0,"ix":5},"nm":"Transform"}],"nm":"Group 3","np":2,"cix":2,"bm":0,"ix":3,"mn":"ADBE Vector Group","hd":false},{"ty":"gr","it":[{"ind":0,"ty":"sh","ix":1,"ks":{"a":0,"k":{"i":[[0,0],[0,0],[0,0]],"o":[[-16.194,7.56],[-11.101,15.517],[0,0]],"v":[[18.761,1.452],[2.248,-9.012],[-18.761,-6.784]],"c":false},"ix":2},"nm":"Path 1","mn":"ADBE Vector Shape - Group","hd":false},{"ty":"st","c":{"a":0,"k":[0.003921568627,0,0.007843137255,1],"ix":3},"o":{"a":0,"k":100,"ix":4},"w":{"a":0,"k":2,"ix":5},"lc":1,"lj":1,"ml":10,"bm":0,"nm":"Stroke 1","mn":"ADBE Vector Graphic - Stroke","hd":false},{"ty":"tr","p":{"a":0,"k":[152.916,181.459],"ix":2},"a":{"a":0,"k":[0,0],"ix":1},"s":{"a":0,"k":[100,100],"ix":3},"r":{"a":0,"k":0,"ix":6},"o":{"a":0,"k":100,"ix":7},"sk":{"a":0,"k":0,"ix":4},"sa":{"a":0,"k":0,"ix":5},"nm":"Transform"}],"nm":"Group 4","np":2,"cix":2,"bm":0,"ix":4,"mn":"ADBE Vector Group","hd":false},{"ty":"gr","it":[{"ind":0,"ty":"sh","ix":1,"ks":{"a":0,"k":{"i":[[-1.5,-0.329],[0,0],[1.363,-0.707],[0,0],[0.486,0.626],[0,0]],"o":[[0,0],[1.499,0.329],[0,0],[-0.703,0.365],[0,0],[-0.941,-1.213]],"v":[[-8.255,-6.111],[9.078,-2.305],[9.482,0.755],[-0.77,6.075],[-2.823,5.623],[-9.904,-3.5]],"c":true},"ix":2},"nm":"Path 1","mn":"ADBE Vector Shape - Group","hd":false},{"ty":"fl","c":{"a":0,"k":[0.003921568627,0,0.007843137255,1],"ix":4},"o":{"a":0,"k":100,"ix":5},"r":1,"bm":0,"nm":"Fill 1","mn":"ADBE Vector Graphic - Fill","hd":false},{"ty":"tr","p":{"a":0,"k":[156.447,164.103],"ix":2},"a":{"a":0,"k":[0,0],"ix":1},"s":{"a":0,"k":[100,100],"ix":3},"r":{"a":0,"k":0,"ix":6},"o":{"a":0,"k":100,"ix":7},"sk":{"a":0,"k":0,"ix":4},"sa":{"a":0,"k":0,"ix":5},"nm":"Transform"}],"nm":"Group 5","np":2,"cix":2,"bm":0,"ix":5,"mn":"ADBE Vector Group","hd":false},{"ty":"gr","it":[{"ind":0,"ty":"sh","ix":1,"ks":{"a":0,"k":{"i":[[0,0],[0,0],[12.914,4.831],[0,0],[0,0],[-60.265,-4.796]],"o":[[-58.144,13.477],[0,0],[-12.915,-4.831],[-21.676,36.301],[0,0],[60.265,4.797]],"v":[[94.618,25.408],[18.709,-21.285],[3.627,-46.554],[-20.891,-32.173],[-94.618,-4.301],[-2.739,46.588]],"c":true},"ix":2},"nm":"Path 1","mn":"ADBE Vector Shape - Group","hd":false},{"ty":"fl","c":{"a":0,"k":[0.784313785329,0.572549019608,0.321568627451,1],"ix":4},"o":{"a":0,"k":100,"ix":5},"r":1,"bm":0,"nm":"Fill 1","mn":"ADBE Vector Graphic - Fill","hd":false},{"ty":"tr","p":{"a":0,"k":[155.111,188.811],"ix":2},"a":{"a":0,"k":[0,0],"ix":1},"s":{"a":0,"k":[100,100],"ix":3},"r":{"a":0,"k":0,"ix":6},"o":{"a":0,"k":100,"ix":7},"sk":{"a":0,"k":0,"ix":4},"sa":{"a":0,"k":0,"ix":5},"nm":"Transform"}],"nm":"Group 6","np":2,"cix":2,"bm":0,"ix":6,"mn":"ADBE Vector Group","hd":false},{"ty":"gr","it":[{"ind":0,"ty":"sh","ix":1,"ks":{"a":0,"k":{"i":[[0,0],[4.281,-0.073],[4.192,-0.941],[2.065,-0.603],[1.91,-1.003],[3.468,-2.562],[-3.931,1.829],[-1.998,0.836],[-2.124,0.445],[-4.339,0.143],[-4.325,-0.802],[0.051,-0.271],[0.271,0.05],[0.002,0]],"o":[[-4.149,-0.853],[-4.293,0.058],[-2.116,0.4],[-1.998,0.792],[-3.95,1.746],[3.416,-2.626],[1.901,-1.045],[2.064,-0.647],[4.207,-1.03],[4.344,-0.153],[0.272,0.05],[-0.05,0.272],[-0.002,-0.001],[0,0]],"v":[[24.02,-4.677],[11.257,-5.774],[-1.516,-4.247],[-7.735,-2.541],[-13.702,-0.088],[-24.696,6.677],[-13.812,-0.313],[-7.859,-2.895],[-1.63,-4.734],[11.235,-6.524],[24.244,-5.651],[24.645,-5.069],[24.063,-4.668],[24.055,-4.669]],"c":true},"ix":2},"nm":"Path 1","mn":"ADBE Vector Shape - Group","hd":false},{"ty":"fl","c":{"a":0,"k":[0.011764706817,0.011764706817,0.011764706817,1],"ix":4},"o":{"a":0,"k":100,"ix":5},"r":1,"bm":0,"nm":"Fill 1","mn":"ADBE Vector Graphic - Fill","hd":false},{"ty":"tr","p":{"a":0,"k":[38.144,168.638],"ix":2},"a":{"a":0,"k":[0,0],"ix":1},"s":{"a":0,"k":[100,100],"ix":3},"r":{"a":0,"k":0,"ix":6},"o":{"a":0,"k":100,"ix":7},"sk":{"a":0,"k":0,"ix":4},"sa":{"a":0,"k":0,"ix":5},"nm":"Transform"}],"nm":"Group 7","np":2,"cix":2,"bm":0,"ix":7,"mn":"ADBE Vector Group","hd":false},{"ty":"gr","it":[{"ind":0,"ty":"sh","ix":1,"ks":{"a":0,"k":{"i":[[0,0],[5.19,1.18],[5.315,0.422],[5.293,-0.683],[2.57,-0.725],[2.403,-1.173],[-2.555,0.796],[-2.646,0.409],[-5.347,-0.336],[-5.248,-1.09],[-5.083,-1.803],[0.092,-0.261],[0.261,0.092],[0.001,0]],"o":[[-4.965,-1.85],[-5.2,-1.165],[-5.313,-0.417],[-2.641,0.366],[-2.56,0.755],[2.384,-1.21],[2.565,-0.768],[5.304,-0.769],[5.349,0.341],[5.248,1.109],[0.26,0.093],[-0.093,0.26],[-0.001,-0.001],[0,0]],"v":[[30.806,3.828],[15.495,-0.657],[-0.296,-3.094],[-16.26,-2.8],[-24.095,-1.197],[-31.56,1.682],[-24.13,-1.318],[-16.296,-3.048],[-0.26,-3.594],[15.654,-1.391],[31.163,2.895],[31.467,3.534],[30.828,3.838],[30.824,3.836]],"c":true},"ix":2},"nm":"Path 1","mn":"ADBE Vector Shape - Group","hd":false},{"ty":"fl","c":{"a":0,"k":[0.011764706817,0.011764706817,0.011764706817,1],"ix":4},"o":{"a":0,"k":100,"ix":5},"r":1,"bm":0,"nm":"Fill 1","mn":"ADBE Vector Graphic - Fill","hd":false},{"ty":"tr","p":{"a":0,"k":[31.81,150.396],"ix":2},"a":{"a":0,"k":[0,0],"ix":1},"s":{"a":0,"k":[100,100],"ix":3},"r":{"a":0,"k":0,"ix":6},"o":{"a":0,"k":100,"ix":7},"sk":{"a":0,"k":0,"ix":4},"sa":{"a":0,"k":0,"ix":5},"nm":"Transform"}],"nm":"Group 8","np":2,"cix":2,"bm":0,"ix":8,"mn":"ADBE Vector Group","hd":false},{"ty":"gr","it":[{"ind":0,"ty":"sh","ix":1,"ks":{"a":0,"k":{"i":[[0,0],[4.875,2.136],[5.141,1.414],[5.328,0.325],[2.66,-0.229],[2.581,-0.7],[-2.66,0.302],[-2.676,-0.096],[-5.188,-1.336],[-4.949,-2.058],[-4.652,-2.727],[0.14,-0.238],[0.238,0.14],[0.002,0.001]],"o":[[-4.528,-2.75],[-4.888,-2.122],[-5.139,-1.41],[-2.662,-0.136],[-2.657,0.26],[2.569,-0.74],[2.663,-0.271],[5.353,0.242],[5.189,1.341],[4.946,2.076],[0.239,0.14],[-0.14,0.239],[-0.002,-0.001],[0,0]],"v":[[30.001,7.778],[15.808,0.493],[0.757,-4.871],[-14.978,-7.587],[-22.973,-7.486],[-30.847,-6.061],[-22.985,-7.609],[-14.965,-7.835],[0.886,-5.355],[16.101,-0.197],[30.528,6.928],[30.707,7.613],[30.023,7.791],[30.018,7.788]],"c":true},"ix":2},"nm":"Path 1","mn":"ADBE Vector Shape - Group","hd":false},{"ty":"fl","c":{"a":0,"k":[0.011764706817,0.011764706817,0.011764706817,1],"ix":4},"o":{"a":0,"k":100,"ix":5},"r":1,"bm":0,"nm":"Fill 1","mn":"ADBE Vector Graphic - Fill","hd":false},{"ty":"tr","p":{"a":0,"k":[34.127,139.108],"ix":2},"a":{"a":0,"k":[0,0],"ix":1},"s":{"a":0,"k":[100,100],"ix":3},"r":{"a":0,"k":0,"ix":6},"o":{"a":0,"k":100,"ix":7},"sk":{"a":0,"k":0,"ix":4},"sa":{"a":0,"k":0,"ix":5},"nm":"Transform"}],"nm":"Group 9","np":2,"cix":2,"bm":0,"ix":9,"mn":"ADBE Vector Group","hd":false},{"ty":"gr","it":[{"ind":0,"ty":"sh","ix":1,"ks":{"a":0,"k":{"i":[[-0.002,0],[-3.881,-1.959],[-3.389,-2.697],[-1.603,-1.451],[-1.288,-1.744],[-2.002,-3.815],[2.855,3.241],[1.483,1.556],[1.754,1.25],[3.875,1.851],[4.125,0.964],[0,0],[-0.063,0.269],[-0.269,-0.062]],"o":[[4.264,1.083],[3.881,1.948],[1.742,1.293],[1.464,1.597],[2.804,3.308],[-2.077,-3.778],[-1.315,-1.711],[-1.622,-1.412],[-3.413,-2.61],[-3.857,-1.858],[0,0],[-0.269,-0.064],[0.062,-0.268],[0.002,0]],"v":[[-19.303,-15.814],[-7.124,-11.158],[3.809,-4.144],[8.695,0.135],[13.019,4.972],[19.975,15.877],[12.826,5.131],[8.434,0.404],[3.503,-3.749],[-7.457,-10.486],[-19.506,-14.835],[-19.539,-14.841],[-19.912,-15.442],[-19.312,-15.815]],"c":true},"ix":2},"nm":"Path 1","mn":"ADBE Vector Shape - Group","hd":false},{"ty":"fl","c":{"a":0,"k":[0.011764706817,0.011764706817,0.011764706817,1],"ix":4},"o":{"a":0,"k":100,"ix":5},"r":1,"bm":0,"nm":"Fill 1","mn":"ADBE Vector Graphic - Fill","hd":false},{"ty":"tr","p":{"a":0,"k":[255.699,212.419],"ix":2},"a":{"a":0,"k":[0,0],"ix":1},"s":{"a":0,"k":[100,100],"ix":3},"r":{"a":0,"k":0,"ix":6},"o":{"a":0,"k":100,"ix":7},"sk":{"a":0,"k":0,"ix":4},"sa":{"a":0,"k":0,"ix":5},"nm":"Transform"}],"nm":"Group 10","np":2,"cix":2,"bm":0,"ix":10,"mn":"ADBE Vector Group","hd":false},{"ty":"gr","it":[{"ind":0,"ty":"sh","ix":1,"ks":{"a":0,"k":{"i":[[-0.002,0],[-5.229,-1.191],[-5,-1.931],[-4.493,-2.919],[-2.008,-1.771],[-1.657,-2.098],[2.009,1.758],[2.244,1.44],[4.999,1.846],[5.209,1.119],[5.283,0.4],[0,0],[-0.021,0.275],[-0.275,-0.02]],"o":[[5.37,0.49],[5.223,1.209],[4.996,1.933],[2.232,1.48],[1.987,1.793],[-1.69,-2.072],[-2.03,-1.736],[-4.521,-2.836],[-5.003,-1.843],[-5.208,-1.103],[0,0],[-0.276,-0.02],[0.021,-0.275],[0.002,0]],"v":[[-28.449,-12.574],[-12.571,-9.97],[2.803,-5.304],[17.135,1.905],[23.525,6.759],[29.014,12.595],[23.443,6.853],[17.001,2.115],[2.627,-4.837],[-12.733,-9.237],[-28.515,-11.577],[-28.532,-11.578],[-28.993,-12.114],[-28.457,-12.575]],"c":true},"ix":2},"nm":"Path 1","mn":"ADBE Vector Shape - Group","hd":false},{"ty":"fl","c":{"a":0,"k":[0.011764706817,0.011764706817,0.011764706817,1],"ix":4},"o":{"a":0,"k":100,"ix":5},"r":1,"bm":0,"nm":"Fill 1","mn":"ADBE Vector Graphic - Fill","hd":false},{"ty":"tr","p":{"a":0,"k":[268.376,200.131],"ix":2},"a":{"a":0,"k":[0,0],"ix":1},"s":{"a":0,"k":[100,100],"ix":3},"r":{"a":0,"k":0,"ix":6},"o":{"a":0,"k":100,"ix":7},"sk":{"a":0,"k":0,"ix":4},"sa":{"a":0,"k":0,"ix":5},"nm":"Transform"}],"nm":"Group 11","np":2,"cix":2,"bm":0,"ix":11,"mn":"ADBE Vector Group","hd":false},{"ty":"gr","it":[{"ind":0,"ty":"sh","ix":1,"ks":{"a":0,"k":{"i":[[0,0],[-5.36,-0.186],[-5.273,-0.956],[-4.962,-2.022],[-2.305,-1.362],[-2.022,-1.749],[2.303,1.349],[2.475,0.991],[5.258,0.873],[5.327,0.12],[5.264,-0.601],[0,0],[0.031,0.274],[-0.274,0.032]],"o":[[5.367,-0.528],[5.357,0.203],[5.271,0.959],[2.47,1.034],[2.289,1.387],[-2.049,-1.717],[-2.321,-1.322],[-4.974,-1.937],[-5.26,-0.869],[-5.322,-0.102],[0,0],[-0.274,0.031],[-0.031,-0.275],[0,0]],"v":[[-30.347,-6.648],[-14.262,-7.076],[1.715,-5.386],[17.148,-1.001],[24.336,2.564],[30.826,7.263],[24.274,2.671],[17.055,-0.769],[1.629,-4.894],[-14.283,-6.328],[-30.224,-5.656],[-30.241,-5.654],[-30.795,-6.094],[-30.355,-6.648]],"c":true},"ix":2},"nm":"Path 1","mn":"ADBE Vector Shape - Group","hd":false},{"ty":"fl","c":{"a":0,"k":[0.011764706817,0.011764706817,0.011764706817,1],"ix":4},"o":{"a":0,"k":100,"ix":5},"r":1,"bm":0,"nm":"Fill 1","mn":"ADBE Vector Graphic - Fill","hd":false},{"ty":"tr","p":{"a":0,"k":[271.784,186.913],"ix":2},"a":{"a":0,"k":[0,0],"ix":1},"s":{"a":0,"k":[100,100],"ix":3},"r":{"a":0,"k":0,"ix":6},"o":{"a":0,"k":100,"ix":7},"sk":{"a":0,"k":0,"ix":4},"sa":{"a":0,"k":0,"ix":5},"nm":"Transform"}],"nm":"Group 12","np":2,"cix":2,"bm":0,"ix":12,"mn":"ADBE Vector Group","hd":false},{"ty":"gr","it":[{"ind":0,"ty":"sh","ix":1,"ks":{"a":0,"k":{"i":[[0,0],[0,0],[-10.114,25.232],[0,0]],"o":[[0,0],[0,0],[0,0],[0,0]],"v":[[-2.582,-28.001],[-8.81,0.373],[2.103,2.769],[8.81,-27.788]],"c":true},"ix":2},"nm":"Path 1","mn":"ADBE Vector Shape - Group","hd":false},{"ty":"fl","c":{"a":0,"k":[0.784313785329,0.572549019608,0.321568627451,1],"ix":4},"o":{"a":0,"k":100,"ix":5},"r":1,"bm":0,"nm":"Fill 1","mn":"ADBE Vector Graphic - Fill","hd":false},{"ty":"tr","p":{"a":0,"k":[147.463,72.706],"ix":2},"a":{"a":0,"k":[0,0],"ix":1},"s":{"a":0,"k":[100,100],"ix":3},"r":{"a":0,"k":0,"ix":6},"o":{"a":0,"k":100,"ix":7},"sk":{"a":0,"k":0,"ix":4},"sa":{"a":0,"k":0,"ix":5},"nm":"Transform"}],"nm":"Group 13","np":2,"cix":2,"bm":0,"ix":13,"mn":"ADBE Vector Group","hd":false},{"ty":"gr","it":[{"ind":0,"ty":"sh","ix":1,"ks":{"a":0,"k":{"i":[[0,0],[-6.069,-3.619],[-0.213,11.392]],"o":[[0,0],[6.068,3.62],[0,0]],"v":[[0.426,-24.115],[-4.79,20.495],[10.859,-19.536]],"c":true},"ix":2},"nm":"Path 1","mn":"ADBE Vector Shape - Group","hd":false},{"ty":"fl","c":{"a":0,"k":[0.784313785329,0.572549019608,0.321568627451,1],"ix":4},"o":{"a":0,"k":100,"ix":5},"r":1,"bm":0,"nm":"Fill 1","mn":"ADBE Vector Graphic - Fill","hd":false},{"ty":"tr","p":{"a":0,"k":[195.134,77.656],"ix":2},"a":{"a":0,"k":[0,0],"ix":1},"s":{"a":0,"k":[100,100],"ix":3},"r":{"a":0,"k":0,"ix":6},"o":{"a":0,"k":100,"ix":7},"sk":{"a":0,"k":0,"ix":4},"sa":{"a":0,"k":0,"ix":5},"nm":"Transform"}],"nm":"Group 14","np":2,"cix":2,"bm":0,"ix":14,"mn":"ADBE Vector Group","hd":false},{"ty":"gr","it":[{"ind":0,"ty":"sh","ix":1,"ks":{"a":0,"k":{"i":[[0,0],[-8.731,-1.916],[0,0]],"o":[[0,0],[8.73,1.917],[0,0]],"v":[[-2.129,-27.016],[-4.418,25.099],[13.148,-23.662]],"c":true},"ix":2},"nm":"Path 1","mn":"ADBE Vector Shape - Group","hd":false},{"ty":"fl","c":{"a":0,"k":[0.784313785329,0.572549019608,0.321568627451,1],"ix":4},"o":{"a":0,"k":100,"ix":5},"r":1,"bm":0,"nm":"Fill 1","mn":"ADBE Vector Graphic - Fill","hd":false},{"ty":"tr","p":{"a":0,"k":[169.794,72.147],"ix":2},"a":{"a":0,"k":[0,0],"ix":1},"s":{"a":0,"k":[100,100],"ix":3},"r":{"a":0,"k":0,"ix":6},"o":{"a":0,"k":100,"ix":7},"sk":{"a":0,"k":0,"ix":4},"sa":{"a":0,"k":0,"ix":5},"nm":"Transform"}],"nm":"Group 15","np":2,"cix":2,"bm":0,"ix":15,"mn":"ADBE Vector Group","hd":false},{"ty":"gr","it":[{"ind":0,"ty":"sh","ix":1,"ks":{"a":0,"k":{"i":[[27.737,-35.01],[69.763,-6.446],[0,0],[0,0],[0,0],[-26.747,-25.211],[0,0]],"o":[[0,0],[-69.762,6.445],[-39.167,-42.443],[52.737,-89.961],[0,0],[22.254,20.977],[0,0]],"v":[[106.549,63.967],[20.16,95.774],[-95.119,46.294],[-119.564,-12.258],[7.101,-95.662],[63.65,-71.162],[103.095,-18.988]],"c":true},"ix":2},"nm":"Path 1","mn":"ADBE Vector Shape - Group","hd":false},{"ty":"fl","c":{"a":0,"k":[0.666666666667,0.411764735802,0.286274509804,1],"ix":4},"o":{"a":0,"k":100,"ix":5},"r":1,"bm":0,"nm":"Fill 1","mn":"ADBE Vector Graphic - Fill","hd":false},{"ty":"tr","p":{"a":0,"k":[156.73,140.486],"ix":2},"a":{"a":0,"k":[0,0],"ix":1},"s":{"a":0,"k":[100,100],"ix":3},"r":{"a":0,"k":0,"ix":6},"o":{"a":0,"k":100,"ix":7},"sk":{"a":0,"k":0,"ix":4},"sa":{"a":0,"k":0,"ix":5},"nm":"Transform"}],"nm":"Group 16","np":2,"cix":2,"bm":0,"ix":16,"mn":"ADBE Vector Group","hd":false},{"ty":"gr","it":[{"ind":0,"ty":"sh","ix":1,"ks":{"a":0,"k":{"i":[[0.372,-0.256],[0,0],[1.859,-3.312],[-11.626,2.938],[0,0],[-11.871,1.97],[0,0],[-15.544,-12.563],[0,0],[-0.617,33.63],[-15.35,7.284],[0,0],[-11.482,3.003],[0,0],[-3.538,-4.243]],"o":[[0,0],[-3.126,2.156],[-2.524,4.497],[0,0],[0,0],[0,0],[0,0],[0,0],[0,0],[0,0],[0,0],[10.916,-4.658],[0,0],[0,0],[0.289,0.346]],"v":[[40.826,-37.836],[8.142,-17.146],[0.449,-8.922],[8.72,-2.329],[3.397,1.078],[8.986,6.88],[3.184,12.47],[0.097,36.957],[2.46,39.314],[-39.699,9.371],[-25.847,-22.141],[-17.621,-25.651],[16.022,-37.159],[28.759,-40.49],[40.632,-38.758]],"c":true},"ix":2},"nm":"Path 1","mn":"ADBE Vector Shape - Group","hd":false},{"ty":"fl","c":{"a":0,"k":[0.407843167174,0.243137269862,0.160784313725,1],"ix":4},"o":{"a":0,"k":100,"ix":5},"r":1,"bm":0,"nm":"Fill 1","mn":"ADBE Vector Graphic - Fill","hd":false},{"ty":"tr","p":{"a":0,"k":[244.83,81.645],"ix":2},"a":{"a":0,"k":[0,0],"ix":1},"s":{"a":0,"k":[100,100],"ix":3},"r":{"a":0,"k":0,"ix":6},"o":{"a":0,"k":100,"ix":7},"sk":{"a":0,"k":0,"ix":4},"sa":{"a":0,"k":0,"ix":5},"nm":"Transform"}],"nm":"Group 17","np":2,"cix":2,"bm":0,"ix":17,"mn":"ADBE Vector Group","hd":false},{"ty":"gr","it":[{"ind":0,"ty":"sh","ix":1,"ks":{"a":0,"k":{"i":[[-52.529,5.057],[3.354,78.519],[12.35,-4.152],[18.631,-7.664],[2.01,-7.724]],"o":[[0,0],[0,0],[0,0],[-7.381,3.035],[-4.739,18.207]],"v":[[8.086,38.833],[41.089,-38.568],[25.332,-39.738],[-23.317,-23.818],[-38.309,-6.731]],"c":true},"ix":2},"nm":"Path 1","mn":"ADBE Vector Shape - Group","hd":false},{"ty":"fl","c":{"a":0,"k":[0.784313785329,0.572549019608,0.321568627451,1],"ix":4},"o":{"a":0,"k":100,"ix":5},"r":1,"bm":0,"nm":"Fill 1","mn":"ADBE Vector Graphic - Fill","hd":false},{"ty":"tr","p":{"a":0,"k":[245.571,81.684],"ix":2},"a":{"a":0,"k":[0,0],"ix":1},"s":{"a":0,"k":[100,100],"ix":3},"r":{"a":0,"k":0,"ix":6},"o":{"a":0,"k":100,"ix":7},"sk":{"a":0,"k":0,"ix":4},"sa":{"a":0,"k":0,"ix":5},"nm":"Transform"}],"nm":"Group 18","np":2,"cix":2,"bm":0,"ix":18,"mn":"ADBE Vector Group","hd":false},{"ty":"gr","it":[{"ind":0,"ty":"sh","ix":1,"ks":{"a":0,"k":{"i":[[-0.23,-0.389],[0,0],[-0.302,-3.786],[9.326,7.538],[0,0],[9.955,6.761],[0,0],[19.376,-4.897],[0,0],[-13.526,30.798],[10.888,13.044],[0,0],[9.169,7.537],[0,0],[4.99,-2.37]],"o":[[0,0],[1.936,3.268],[0.408,5.141],[0,0],[0,0],[0,0],[0,0],[0,0],[0,0],[0,0],[0,0],[-7.961,-8.801],[0,0],[0,0],[-0.407,0.194]],"v":[[-32.314,-52.132],[-11.301,-19.656],[-7.758,-8.966],[-18.03,-6.443],[-14.624,-1.12],[-22.129,1.807],[-19.202,9.313],[-26.654,32.842],[-29.788,33.993],[21.038,24.459],[21.656,-9.956],[15.656,-16.589],[-10.074,-41.13],[-20.245,-49.487],[-31.751,-52.888]],"c":true},"ix":2},"nm":"Path 1","mn":"ADBE Vector Shape - Group","hd":false},{"ty":"fl","c":{"a":0,"k":[0.407843167174,0.243137269862,0.160784313725,1],"ix":4},"o":{"a":0,"k":100,"ix":5},"r":1,"bm":0,"nm":"Fill 1","mn":"ADBE Vector Graphic - Fill","hd":false},{"ty":"tr","p":{"a":0,"k":[108.559,56.838],"ix":2},"a":{"a":0,"k":[0,0],"ix":1},"s":{"a":0,"k":[100,100],"ix":3},"r":{"a":0,"k":0,"ix":6},"o":{"a":0,"k":100,"ix":7},"sk":{"a":0,"k":0,"ix":4},"sa":{"a":0,"k":0,"ix":5},"nm":"Transform"}],"nm":"Group 19","np":2,"cix":2,"bm":0,"ix":19,"mn":"ADBE Vector Group","hd":false},{"ty":"gr","it":[{"ind":0,"ty":"sh","ix":1,"ks":{"a":0,"k":{"i":[[45.583,26.592],[-35.931,69.895],[-9.476,-8.943],[-13.708,-14.761],[1.41,-7.856]],"o":[[0,0],[0,0],[0,0],[5.431,5.848],[-3.322,18.518]],"v":[[-14.57,30.461],[-12.122,-53.647],[2.676,-48.111],[40.185,-13.28],[46.643,8.517]],"c":true},"ix":2},"nm":"Path 1","mn":"ADBE Vector Shape - Group","hd":false},{"ty":"fl","c":{"a":0,"k":[0.784313785329,0.572549019608,0.321568627451,1],"ix":4},"o":{"a":0,"k":100,"ix":5},"r":1,"bm":0,"nm":"Fill 1","mn":"ADBE Vector Graphic - Fill","hd":false},{"ty":"tr","p":{"a":0,"k":[87.745,57.304],"ix":2},"a":{"a":0,"k":[0,0],"ix":1},"s":{"a":0,"k":[100,100],"ix":3},"r":{"a":0,"k":0,"ix":6},"o":{"a":0,"k":100,"ix":7},"sk":{"a":0,"k":0,"ix":4},"sa":{"a":0,"k":0,"ix":5},"nm":"Transform"}],"nm":"Group 20","np":2,"cix":2,"bm":0,"ix":20,"mn":"ADBE Vector Group","hd":false},{"ty":"gr","it":[{"ind":0,"ty":"sh","ix":1,"ks":{"a":0,"k":{"i":[[0,0],[163.693,-7.385]],"o":[[0,0],[0,0]],"v":[[0.661,-58.469],[-81.846,58.469]],"c":true},"ix":2},"nm":"Path 1","mn":"ADBE Vector Shape - Group","hd":false},{"ty":"fl","c":{"a":0,"k":[0.407843167174,0.243137269862,0.160784313725,1],"ix":4},"o":{"a":0,"k":100,"ix":5},"r":1,"bm":0,"nm":"Fill 1","mn":"ADBE Vector Graphic - Fill","hd":false},{"ty":"tr","p":{"a":0,"k":[257.681,177.295],"ix":2},"a":{"a":0,"k":[0,0],"ix":1},"s":{"a":0,"k":[100,100],"ix":3},"r":{"a":0,"k":0,"ix":6},"o":{"a":0,"k":100,"ix":7},"sk":{"a":0,"k":0,"ix":4},"sa":{"a":0,"k":0,"ix":5},"nm":"Transform"}],"nm":"Group 21","np":2,"cix":2,"bm":0,"ix":21,"mn":"ADBE Vector Group","hd":false}],"ip":0,"op":150,"st":0,"bm":0},{"ddd":0,"ind":12,"ty":4,"nm":"Body","sr":1,"ks":{"o":{"a":0,"k":100,"ix":11},"r":{"a":0,"k":0,"ix":10},"p":{"a":1,"k":[{"i":{"x":0.667,"y":1},"o":{"x":0.333,"y":0},"t":0,"s":[514.102,486.573,0],"to":[-0.5,0.5,0],"ti":[0,0,0]},{"i":{"x":0.667,"y":1},"o":{"x":0.333,"y":0},"t":74.5,"s":[511.102,489.573,0],"to":[0,0,0],"ti":[-0.5,0.5,0]},{"t":149,"s":[514.102,486.573,0]}],"ix":2,"l":2},"a":{"a":0,"k":[230.342,139.068,0],"ix":1,"l":2},"s":{"a":0,"k":[150,150,100],"ix":6,"l":2}},"ao":0,"shapes":[{"ty":"gr","it":[{"ind":0,"ty":"sh","ix":1,"ks":{"a":0,"k":{"i":[[-8.629,12.654],[56.142,4.183],[0,-29.826],[-26.62,-4.096]],"o":[[20.478,-30.033],[-37.305,-2.78],[0,29.824],[9.323,1.433]],"v":[[40.997,49.302],[-0.107,-59.176],[-61.475,0.499],[-12.33,56.812]],"c":true},"ix":2},"nm":"Path 1","mn":"ADBE Vector Shape - Group","hd":false},{"ty":"fl","c":{"a":0,"k":[0.666666666667,0.411764735802,0.286274509804,1],"ix":4},"o":{"a":0,"k":100,"ix":5},"r":1,"bm":0,"nm":"Fill 1","mn":"ADBE Vector Graphic - Fill","hd":false},{"ty":"tr","p":{"a":0,"k":[393.329,199.527],"ix":2},"a":{"a":0,"k":[0,0],"ix":1},"s":{"a":0,"k":[100,100],"ix":3},"r":{"a":0,"k":0,"ix":6},"o":{"a":0,"k":100,"ix":7},"sk":{"a":0,"k":0,"ix":4},"sa":{"a":0,"k":0,"ix":5},"nm":"Transform"}],"nm":"Group 22","np":2,"cix":2,"bm":0,"ix":1,"mn":"ADBE Vector Group","hd":false},{"ty":"gr","it":[{"ind":0,"ty":"sh","ix":1,"ks":{"a":0,"k":{"i":[[4.485,-1.734],[22.551,-8.827],[-0.294,-8.362],[-2.861,-0.101],[-6.896,1.549],[-8.479,16.575]],"o":[[-15.804,17.152],[-11.242,4.401],[0.193,5.502],[9.447,0.329],[11.674,-2.619],[-7.902,-1.735]],"v":[[11.81,-24.091],[-51.02,-3.278],[-69.232,17.528],[-60.768,25.495],[57.852,24.197],[67.435,-13.299]],"c":true},"ix":2},"nm":"Path 1","mn":"ADBE Vector Shape - Group","hd":false},{"ty":"fl","c":{"a":0,"k":[0.666666666667,0.411764735802,0.286274509804,1],"ix":4},"o":{"a":0,"k":100,"ix":5},"r":1,"bm":0,"nm":"Fill 1","mn":"ADBE Vector Graphic - Fill","hd":false},{"ty":"tr","p":{"a":0,"k":[369.621,252.062],"ix":2},"a":{"a":0,"k":[0,0],"ix":1},"s":{"a":0,"k":[100,100],"ix":3},"r":{"a":0,"k":0,"ix":6},"o":{"a":0,"k":100,"ix":7},"sk":{"a":0,"k":0,"ix":4},"sa":{"a":0,"k":0,"ix":5},"nm":"Transform"}],"nm":"Group 23","np":2,"cix":2,"bm":0,"ix":2,"mn":"ADBE Vector Group","hd":false},{"ty":"gr","it":[{"ind":0,"ty":"sh","ix":1,"ks":{"a":0,"k":{"i":[[57.956,4.003],[0,-28.527],[-4.245,-8.916],[8.436,-4.094],[-0.292,-8.36],[-2.86,-0.101],[-8.08,10.982]],"o":[[-38.514,-2.661],[0,11.536],[-4.433,1.928],[-10.86,5.272],[1.67,0.257],[5.589,0.195],[21.142,-28.725]],"v":[[18.014,-56.622],[-45.337,0.453],[-39.957,27.963],[-57.368,35.029],[-75.678,59.023],[-61.16,59.087],[53.975,45.795]],"c":true},"ix":2},"nm":"Path 1","mn":"ADBE Vector Shape - Group","hd":false},{"ty":"fl","c":{"a":0,"k":[0.407843167174,0.243137269862,0.160784313725,1],"ix":4},"o":{"a":0,"k":100,"ix":5},"r":1,"bm":0,"nm":"Fill 1","mn":"ADBE Vector Graphic - Fill","hd":false},{"ty":"tr","p":{"a":0,"k":[369.514,209.708],"ix":2},"a":{"a":0,"k":[0,0],"ix":1},"s":{"a":0,"k":[100,100],"ix":3},"r":{"a":0,"k":0,"ix":6},"o":{"a":0,"k":100,"ix":7},"sk":{"a":0,"k":0,"ix":4},"sa":{"a":0,"k":0,"ix":5},"nm":"Transform"}],"nm":"Group 24","np":2,"cix":2,"bm":0,"ix":3,"mn":"ADBE Vector Group","hd":false},{"ty":"gr","it":[{"ind":0,"ty":"sh","ix":1,"ks":{"a":0,"k":{"i":[[4.485,-1.734],[22.55,-8.827],[-0.293,-8.362],[-2.861,-0.101],[-6.897,1.549],[-8.479,16.575]],"o":[[-15.804,17.152],[-11.242,4.401],[0.193,5.502],[9.447,0.329],[11.671,-2.619],[-7.9,-1.735]],"v":[[12.049,-24.091],[-50.781,-3.278],[-68.993,17.528],[-60.529,25.495],[40.687,24.197],[69.286,-13.299]],"c":true},"ix":2},"nm":"Path 1","mn":"ADBE Vector Shape - Group","hd":false},{"ty":"fl","c":{"a":0,"k":[0.666666666667,0.411764735802,0.286274509804,1],"ix":4},"o":{"a":0,"k":100,"ix":5},"r":1,"bm":0,"nm":"Fill 1","mn":"ADBE Vector Graphic - Fill","hd":false},{"ty":"tr","p":{"a":0,"k":[162.563,252.062],"ix":2},"a":{"a":0,"k":[0,0],"ix":1},"s":{"a":0,"k":[100,100],"ix":3},"r":{"a":0,"k":0,"ix":6},"o":{"a":0,"k":100,"ix":7},"sk":{"a":0,"k":0,"ix":4},"sa":{"a":0,"k":0,"ix":5},"nm":"Transform"}],"nm":"Group 25","np":2,"cix":2,"bm":0,"ix":4,"mn":"ADBE Vector Group","hd":false},{"ty":"gr","it":[{"ind":0,"ty":"sh","ix":1,"ks":{"a":0,"k":{"i":[[-4.32,0.411],[0.83,15.808],[4.467,1.71]],"o":[[4.102,-0.389],[-3.891,-2.273],[2.44,19.736]],"v":[[1.629,21.882],[5.855,-16.334],[-6.685,-22.293]],"c":true},"ix":2},"nm":"Path 1","mn":"ADBE Vector Shape - Group","hd":false},{"ty":"fl","c":{"a":0,"k":[0.784313785329,0.572549019608,0.321568627451,1],"ix":4},"o":{"a":0,"k":100,"ix":5},"r":1,"bm":0,"nm":"Fill 1","mn":"ADBE Vector Graphic - Fill","hd":false},{"ty":"tr","p":{"a":0,"k":[397.887,153.633],"ix":2},"a":{"a":0,"k":[0,0],"ix":1},"s":{"a":0,"k":[100,100],"ix":3},"r":{"a":0,"k":0,"ix":6},"o":{"a":0,"k":100,"ix":7},"sk":{"a":0,"k":0,"ix":4},"sa":{"a":0,"k":0,"ix":5},"nm":"Transform"}],"nm":"Group 26","np":2,"cix":2,"bm":0,"ix":5,"mn":"ADBE Vector Group","hd":false},{"ty":"gr","it":[{"ind":0,"ty":"sh","ix":1,"ks":{"a":0,"k":{"i":[[-6.834,0.421],[0.06,26.903],[4.672,-0.427]],"o":[[7.034,-0.437],[-5.1,-0.007],[2.706,27.609]],"v":[[1.639,38.508],[6.012,-38.922],[-8.673,-38.311]],"c":true},"ix":2},"nm":"Path 1","mn":"ADBE Vector Shape - Group","hd":false},{"ty":"fl","c":{"a":0,"k":[0.784313785329,0.572549019608,0.321568627451,1],"ix":4},"o":{"a":0,"k":100,"ix":5},"r":1,"bm":0,"nm":"Fill 1","mn":"ADBE Vector Graphic - Fill","hd":false},{"ty":"tr","p":{"a":0,"k":[330.197,160.512],"ix":2},"a":{"a":0,"k":[0,0],"ix":1},"s":{"a":0,"k":[100,100],"ix":3},"r":{"a":0,"k":0,"ix":6},"o":{"a":0,"k":100,"ix":7},"sk":{"a":0,"k":0,"ix":4},"sa":{"a":0,"k":0,"ix":5},"nm":"Transform"}],"nm":"Group 27","np":2,"cix":2,"bm":0,"ix":6,"mn":"ADBE Vector Group","hd":false},{"ty":"gr","it":[{"ind":0,"ty":"sh","ix":1,"ks":{"a":0,"k":{"i":[[-7.127,0.977],[2.626,24.15],[4.212,0.496]],"o":[[5.616,-0.768],[-4.473,-0.88],[3.426,25.305]],"v":[[4.594,34.904],[2.818,-33.82],[-10.21,-35.881]],"c":true},"ix":2},"nm":"Path 1","mn":"ADBE Vector Shape - Group","hd":false},{"ty":"fl","c":{"a":0,"k":[0.784313785329,0.572549019608,0.321568627451,1],"ix":4},"o":{"a":0,"k":100,"ix":5},"r":1,"bm":0,"nm":"Fill 1","mn":"ADBE Vector Graphic - Fill","hd":false},{"ty":"tr","p":{"a":0,"k":[364.89,158.591],"ix":2},"a":{"a":0,"k":[0,0],"ix":1},"s":{"a":0,"k":[100,100],"ix":3},"r":{"a":0,"k":0,"ix":6},"o":{"a":0,"k":100,"ix":7},"sk":{"a":0,"k":0,"ix":4},"sa":{"a":0,"k":0,"ix":5},"nm":"Transform"}],"nm":"Group 28","np":2,"cix":2,"bm":0,"ix":7,"mn":"ADBE Vector Group","hd":false},{"ty":"gr","it":[{"ind":0,"ty":"sh","ix":1,"ks":{"a":0,"k":{"i":[[-5.518,-1.055],[-5.034,19.365],[4.421,0.582]],"o":[[5.756,1.101],[-5.8,1.395],[-2.666,19.947]],"v":[[-4.303,18.85],[9.822,-19.951],[-5.48,-18.44]],"c":true},"ix":2},"nm":"Path 1","mn":"ADBE Vector Shape - Group","hd":false},{"ty":"fl","c":{"a":0,"k":[0.278431372549,0.278431372549,0.278431372549,1],"ix":4},"o":{"a":0,"k":100,"ix":5},"r":1,"bm":0,"nm":"Fill 1","mn":"ADBE Vector Graphic - Fill","hd":false},{"ty":"tr","p":{"a":0,"k":[253.244,155.506],"ix":2},"a":{"a":0,"k":[0,0],"ix":1},"s":{"a":0,"k":[100,100],"ix":3},"r":{"a":0,"k":0,"ix":6},"o":{"a":0,"k":100,"ix":7},"sk":{"a":0,"k":0,"ix":4},"sa":{"a":0,"k":0,"ix":5},"nm":"Transform"}],"nm":"Group 29","np":2,"cix":2,"bm":0,"ix":8,"mn":"ADBE Vector Group","hd":false},{"ty":"gr","it":[{"ind":0,"ty":"sh","ix":1,"ks":{"a":0,"k":{"i":[[4.833,-1.365],[-5.518,-0.664],[-2.282,27.895]],"o":[[-1.126,30.099],[5.46,0.655],[-5.55,1.195]],"v":[[-7.042,-33.232],[-3.034,36.473],[8.552,-37.129]],"c":true},"ix":2},"nm":"Path 1","mn":"ADBE Vector Shape - Group","hd":false},{"ty":"fl","c":{"a":0,"k":[0.784313785329,0.572549019608,0.321568627451,1],"ix":4},"o":{"a":0,"k":100,"ix":5},"r":1,"bm":0,"nm":"Fill 1","mn":"ADBE Vector Graphic - Fill","hd":false},{"ty":"tr","p":{"a":0,"k":[292.212,162.547],"ix":2},"a":{"a":0,"k":[0,0],"ix":1},"s":{"a":0,"k":[100,100],"ix":3},"r":{"a":0,"k":0,"ix":6},"o":{"a":0,"k":100,"ix":7},"sk":{"a":0,"k":0,"ix":4},"sa":{"a":0,"k":0,"ix":5},"nm":"Transform"}],"nm":"Group 30","np":2,"cix":2,"bm":0,"ix":9,"mn":"ADBE Vector Group","hd":false},{"ty":"gr","it":[{"ind":0,"ty":"sh","ix":1,"ks":{"a":0,"k":{"i":[[8.663,-24.942],[14.728,0.68],[2.985,7.165],[-34.817,5.06]],"o":[[-8.473,24.396],[-21.503,-0.993],[10.405,-20.813],[21.3,-3.095]],"v":[[32.922,-1.777],[-6.144,56.643],[-36.17,13.748],[-6.768,-54.229]],"c":true},"ix":2},"nm":"Path 1","mn":"ADBE Vector Shape - Group","hd":false},{"ty":"fl","c":{"a":0,"k":[0.666666666667,0.411764735802,0.286274509804,1],"ix":4},"o":{"a":0,"k":100,"ix":5},"r":1,"bm":0,"nm":"Fill 1","mn":"ADBE Vector Graphic - Fill","hd":false},{"ty":"tr","p":{"a":0,"k":[208.277,220.172],"ix":2},"a":{"a":0,"k":[0,0],"ix":1},"s":{"a":0,"k":[100,100],"ix":3},"r":{"a":0,"k":0,"ix":6},"o":{"a":0,"k":100,"ix":7},"sk":{"a":0,"k":0,"ix":4},"sa":{"a":0,"k":0,"ix":5},"nm":"Transform"}],"nm":"Group 31","np":2,"cix":2,"bm":0,"ix":10,"mn":"ADBE Vector Group","hd":false},{"ty":"gr","it":[{"ind":0,"ty":"sh","ix":1,"ks":{"a":0,"k":{"i":[[21.921,7.154],[0.77,29.679],[0.377,27.13],[-14.108,1.137],[-9.12,-19.841],[-79.444,-4.047]],"o":[[-30.515,-9.957],[-0.659,-25.354],[3.697,0.232],[-67.454,35.656],[19.044,41.424],[-67.262,2.121]],"v":[[-49.491,62.153],[-102.683,2.987],[-94.203,-77.574],[-6.513,-53.868],[-42.402,31.907],[103.342,75.452]],"c":true},"ix":2},"nm":"Path 1","mn":"ADBE Vector Shape - Group","hd":false},{"ty":"fl","c":{"a":0,"k":[0.784313785329,0.572549019608,0.321568627451,1],"ix":4},"o":{"a":0,"k":100,"ix":5},"r":1,"bm":0,"nm":"Fill 1","mn":"ADBE Vector Graphic - Fill","hd":false},{"ty":"tr","p":{"a":0,"k":[231.232,193.954],"ix":2},"a":{"a":0,"k":[0,0],"ix":1},"s":{"a":0,"k":[100,100],"ix":3},"r":{"a":0,"k":0,"ix":6},"o":{"a":0,"k":100,"ix":7},"sk":{"a":0,"k":0,"ix":4},"sa":{"a":0,"k":0,"ix":5},"nm":"Transform"}],"nm":"Group 32","np":2,"cix":2,"bm":0,"ix":11,"mn":"ADBE Vector Group","hd":false},{"ty":"gr","it":[{"ind":0,"ty":"sh","ix":1,"ks":{"a":0,"k":{"i":[[0.733,16.008],[8.094,0.526],[-3.982,-22.495],[-34.6,-12.562],[-23.092,13.446],[70.987,20.989],[22.525,7.678]],"o":[[0.464,15.303],[-5.922,28.612],[3.206,18.1],[47.598,17.282],[26.96,-15.7],[-76.755,-22.694],[-12.591,-4.292]],"v":[[-68.087,-79.587],[-152.225,-61.051],[-162.766,7.762],[-106.611,66.503],[139.788,69.111],[90.983,-61.091],[-49.628,-53.668]],"c":true},"ix":2},"nm":"Path 1","mn":"ADBE Vector Shape - Group","hd":false},{"ty":"fl","c":{"a":0,"k":[0.666666666667,0.411764735802,0.286274509804,1],"ix":4},"o":{"a":0,"k":100,"ix":5},"r":1,"bm":0,"nm":"Fill 1","mn":"ADBE Vector Graphic - Fill","hd":false},{"ty":"tr","p":{"a":0,"k":[293.686,189.958],"ix":2},"a":{"a":0,"k":[0,0],"ix":1},"s":{"a":0,"k":[100,100],"ix":3},"r":{"a":0,"k":0,"ix":6},"o":{"a":0,"k":100,"ix":7},"sk":{"a":0,"k":0,"ix":4},"sa":{"a":0,"k":0,"ix":5},"nm":"Transform"}],"nm":"Group 33","np":2,"cix":2,"bm":0,"ix":12,"mn":"ADBE Vector Group","hd":false},{"ty":"gr","it":[{"ind":0,"ty":"sh","ix":1,"ks":{"a":0,"k":{"i":[[4.486,-1.732],[22.505,-8.941],[0.326,-8.359],[-2.863,-0.102],[-6.896,1.549],[-8.479,16.573]],"o":[[-15.803,17.155],[-9.541,3.79],[-0.154,3.962],[9.445,0.331],[11.674,-2.622],[-7.9,-1.734]],"v":[[23.679,-24.093],[-51.059,-1.768],[-68.597,17.696],[-61.064,25.494],[40.148,24.198],[68.752,-13.299]],"c":true},"ix":2},"nm":"Path 1","mn":"ADBE Vector Shape - Group","hd":false},{"ty":"fl","c":{"a":0,"k":[0.666666666667,0.411764735802,0.286274509804,1],"ix":4},"o":{"a":0,"k":100,"ix":5},"r":1,"bm":0,"nm":"Fill 1","mn":"ADBE Vector Graphic - Fill","hd":false},{"ty":"tr","p":{"a":0,"k":[110.997,219.138],"ix":2},"a":{"a":0,"k":[0,0],"ix":1},"s":{"a":0,"k":[100,100],"ix":3},"r":{"a":0,"k":0,"ix":6},"o":{"a":0,"k":100,"ix":7},"sk":{"a":0,"k":0,"ix":4},"sa":{"a":0,"k":0,"ix":5},"nm":"Transform"}],"nm":"Group 34","np":2,"cix":2,"bm":0,"ix":13,"mn":"ADBE Vector Group","hd":false},{"ty":"gr","it":[{"ind":0,"ty":"sh","ix":1,"ks":{"a":0,"k":{"i":[[3.815,-5.274],[0,0],[-2.202,18.816]],"o":[[-7.08,9.792],[0,0],[5.521,-3.376]],"v":[[6.583,12.049],[-11.291,11.674],[5.77,-18.465]],"c":true},"ix":2},"nm":"Path 1","mn":"ADBE Vector Shape - Group","hd":false},{"ty":"fl","c":{"a":0,"k":[0.482352971096,0.482352971096,0.482352971096,1],"ix":4},"o":{"a":0,"k":100,"ix":5},"r":1,"bm":0,"nm":"Fill 1","mn":"ADBE Vector Graphic - Fill","hd":false},{"ty":"tr","p":{"a":0,"k":[127.601,170.812],"ix":2},"a":{"a":0,"k":[0,0],"ix":1},"s":{"a":0,"k":[100,100],"ix":3},"r":{"a":0,"k":0,"ix":6},"o":{"a":0,"k":100,"ix":7},"sk":{"a":0,"k":0,"ix":4},"sa":{"a":0,"k":0,"ix":5},"nm":"Transform"}],"nm":"Group 35","np":2,"cix":2,"bm":0,"ix":14,"mn":"ADBE Vector Group","hd":false},{"ty":"gr","it":[{"ind":0,"ty":"sh","ix":1,"ks":{"a":0,"k":{"i":[[4.341,-3.709],[0,0],[-4.723,19.081]],"o":[[-9.925,8.48],[0,0],[4.901,-2.93]],"v":[[5.018,7.103],[-10.979,5.271],[6.078,-12.653]],"c":true},"ix":2},"nm":"Path 1","mn":"ADBE Vector Shape - Group","hd":false},{"ty":"fl","c":{"a":0,"k":[0.482352971096,0.482352971096,0.482352971096,1],"ix":4},"o":{"a":0,"k":100,"ix":5},"r":1,"bm":0,"nm":"Fill 1","mn":"ADBE Vector Graphic - Fill","hd":false},{"ty":"tr","p":{"a":0,"k":[130.662,153.799],"ix":2},"a":{"a":0,"k":[0,0],"ix":1},"s":{"a":0,"k":[100,100],"ix":3},"r":{"a":0,"k":0,"ix":6},"o":{"a":0,"k":100,"ix":7},"sk":{"a":0,"k":0,"ix":4},"sa":{"a":0,"k":0,"ix":5},"nm":"Transform"}],"nm":"Group 36","np":2,"cix":2,"bm":0,"ix":15,"mn":"ADBE Vector Group","hd":false}],"ip":0,"op":150,"st":0,"bm":0}]}],"layers":[{"ddd":0,"ind":1,"ty":0,"nm":"05","refId":"comp_0","sr":1,"ks":{"o":{"a":0,"k":100,"ix":11},"r":{"a":0,"k":0,"ix":10},"p":{"a":0,"k":[540,540,0],"ix":2,"l":2},"a":{"a":0,"k":[540,540,0],"ix":1,"l":2},"s":{"a":0,"k":[100,100,100],"ix":6,"l":2}},"ao":0,"w":1080,"h":1080,"ip":0,"op":150,"st":0,"bm":0}],"markers":[]}